hypertag/__init__.py
hypertag/builtins.py
hypertag/html.py
hypertag/core/__init__.py
hypertag/core/ast.py
hypertag/core/dom.py
hypertag/core/errors.py
hypertag/core/grammar.py
hypertag/core/run_html.py
hypertag/core/runtime.py
hypertag/core/structs.py
hypertag/core/tag.py
hypertag/core/xml_chars.py
hypertag/django/__init__.py
hypertag/django/backend.py
hypertag/django/filters.py
hypertag/nifty/__init__.py
hypertag/nifty/parsing.py
hypertag/nifty/util.py
hypertag/std/__init__.py
hypertag/std/builtins.py
hypertag/std/html.py
hypertag/std/registry.py
hypertag/tests/__init__.py
hypertag/tests/sample1.py
hypertag/tests/package1/__init__.py
hypertag_lang-1.2.0.dist-info/LICENSE
hypertag_lang-1.2.0.dist-info/METADATA
hypertag_lang-1.2.0.dist-info/WHEEL
hypertag_lang-1.2.0.dist-info/top_level.txt
hypertag_lang-1.2.0.dist-info/RECORD
