Metadata-Version: 2.1
Name: hypertag-lang
Version: 1.2.0
Summary: Modern language for markup generation with Python-like concise syntax, custom tags & Django integration. HTML templates reinvented.
Home-page: http://hypertag.io/
Author: Marcin Wojnarski
Author-email: hypertag@paperity.org
License: UNKNOWN
Project-URL: Source, https://github.com/mwojnars/hypertag
Keywords: markup,language,html,html5,css,templates,templating,tags,jinja2,mako,django,DOM
Platform: UNKNOWN
Classifier: Programming Language :: Python :: 3
Classifier: License :: OSI Approved :: MIT License
Classifier: Operating System :: OS Independent
Requires-Python: >=3.5
License-File: LICENSE
Requires-Dist: parsimonious (==0.8.1)
Requires-Dist: six (>=1.12.0)
